Metadata-Version: 1.0
Name: getcite
Version: 1.3.25
Summary: Pulls original sources from Westlaw and HeinOnline.org
Home-page: UNKNOWN
Author: Samuel Alexander
Author-email: salexander2000@gmail.com
License: GPL
Platform: UNKNOWN
